download_oscar/__init__.py
download_oscar/dod.py
download_oscar/dod_gui.py
download_oscar/status.py
download_oscar-2.1.dist-info/LICENSE
download_oscar-2.1.dist-info/METADATA
download_oscar-2.1.dist-info/WHEEL
download_oscar-2.1.dist-info/entry_points.txt
download_oscar-2.1.dist-info/top_level.txt
download_oscar-2.1.dist-info/RECORD
