Metadata-Version: 2.1
Name: download-oscar
Version: 2.1
Summary: Downloading all files of a language from the OSCAR (Open Super-large Crawled Aggregated coRpus)
Home-page: https://github.com/xamm/download_oscar
Download-URL: https://pypi.org/project/download-oscar/
Author: xamm
Author-email: xamm.apps@gmail.com
License: MIT
Keywords: nlp,dataset,automation
Platform: UNKNOWN
Classifier: Development Status :: 5 - Production/Stable
Classifier: Intended Audience :: Science/Research
Classifier: Topic :: Scientific/Engineering :: Artificial Intelligence
Classifier: License :: OSI Approved :: MIT License
Classifier: Programming Language :: Python :: 3
License-File: LICENSE
Requires-Dist: beautifulsoup4
Requires-Dist: html5lib
Requires-Dist: PySimpleGUI
Requires-Dist: requests
Requires-Dist: tqdm
